scooch/__init__.py
scooch/config.py
scooch/config_collection.py
scooch/config_factory.py
scooch/config_list.py
scooch/configurable.py
scooch/configurable_factory.py
scooch/configurable_meta.py
scooch/configurable_param.py
scooch/configurize_helper.py
scooch/generic.py
scooch/param.py
scooch/cli/__init__.py
scooch/cli/cli.py
scooch/cli/export.py
scooch/cli/options.py
scooch-1.0.1.dist-info/LICENSE
scooch-1.0.1.dist-info/METADATA
scooch-1.0.1.dist-info/WHEEL
scooch-1.0.1.dist-info/entry_points.txt
scooch-1.0.1.dist-info/top_level.txt
scooch-1.0.1.dist-info/RECORD
