Metadata-Version: 2.1
Name: scooch
Version: 1.0.1
Summary: A python module for configuring hierarchical class structures in yaml with defaults
Home-page: http://www.mattcmccallum.com/scooch/docs
Author: Matt C. McCallum
Author-email: scooch@mattcmccallum.com
License: Apache 2.0
Project-URL: Documentation, http://www.mattcmccallum.com/scooch/docs
Project-URL: Bug Reports, https://github.com/PandoraMedia/scooch/issues
Project-URL: Source, https://github.com/PandoraMedia/scooch
Keywords: scooch python configuration machine learning
Platform: UNKNOWN
Classifier: Development Status :: 5 - Production/Stable
Classifier: Intended Audience :: Developers
Classifier: Intended Audience :: Education
Classifier: Intended Audience :: Science/Research
Classifier: License :: OSI Approved :: Apache Software License
Classifier: Programming Language :: Python :: 3.6
Classifier: Programming Language :: Python :: 3.7
Classifier: Programming Language :: Python :: 3.8
Classifier: Programming Language :: Python :: 3.9
Classifier: Programming Language :: Python :: 3.10
Classifier: Topic :: Scientific/Engineering
Classifier: Topic :: Scientific/Engineering :: Mathematics
Classifier: Topic :: Scientific/Engineering :: Artificial Intelligence
Classifier: Topic :: Software Development
Classifier: Topic :: Software Development :: Libraries
Classifier: Topic :: Software Development :: Libraries :: Python Modules
Requires-Python: >=3.6
License-File: LICENSE
Requires-Dist: pyyaml (==5.4.1)
Requires-Dist: sphinx
Requires-Dist: sphinx-rtd-theme (==0.5.1)
Requires-Dist: ruamel.yaml (==0.16.12)
Requires-Dist: click (==8.0.0a1)
